README.md
setup.py
distributions_ems/Binomialdistribution.py
distributions_ems/Gaussiandistribution.py
distributions_ems/Generaldistribution.py
distributions_ems/__init__.py
distributions_ems.egg-info/PKG-INFO
distributions_ems.egg-info/SOURCES.txt
distributions_ems.egg-info/dependency_links.txt
distributions_ems.egg-info/not-zip-safe
distributions_ems.egg-info/top_level.txt